{
  "inference_mode": "local",
  "samples_processed": 45882,
  "total_docs": 45882,
  "inference_time_seconds": 263.1450397968292,
  "total_topics": 57,
  "model_path": "/Users/mark/Documents/work/bluesky-research/services/calculate_analytics/analyses/calculate_feed_topic_models_2025_08_18/train/trained_models/local/20250910_121807/model",
  "metadata_path": "/Users/mark/Documents/work/bluesky-research/services/calculate_analytics/analyses/calculate_feed_topic_models_2025_08_18/train/trained_models/local/20250910_121807/metadata/model_metadata.json",
  "inference_timestamp": "2025-09-16-16:53:13",
  "topic_distribution": {
    "-1": 30034,
    "0": 13354,
    "10": 159,
    "27": 150,
    "5": 131,
    "53": 103,
    "43": 96,
    "6": 90,
    "1": 78,
    "12": 77,
    "20": 76,
    "8": 70,
    "14": 69,
    "40": 63,
    "2": 61,
    "34": 55,
    "55": 54,
    "3": 53,
    "25": 52,
    "22": 51,
    "9": 51,
    "19": 50,
    "32": 44,
    "29": 44,
    "26": 44,
    "49": 43,
    "39": 40,
    "35": 35,
    "21": 35,
    "52": 33,
    "11": 33,
    "4": 33,
    "17": 32,
    "31": 31,
    "38": 31,
    "24": 30,
    "46": 30,
    "28": 25,
    "47": 25,
    "15": 24,
    "16": 24,
    "33": 24,
    "23": 24,
    "18": 24,
    "42": 23,
    "50": 21,
    "13": 21,
    "51": 19,
    "56": 19,
    "45": 18,
    "7": 18,
    "54": 18,
    "41": 17,
    "30": 10,
    "37": 8,
    "44": 3,
    "48": 2
  }
}