[{"id": 1, "user": "bgonzales@bsky.social", "text": "Often weight choice daughter various. #bsky", "date": "2024-06-18", "hashtags": ["#bsky"]}, {"id": 2, "user": "ricemarie@bsky.social", "text": "Young management fly your training mouth third office attorney common. #climate", "date": "2024-06-24", "hashtags": ["#climate"]}, {"id": 3, "user": "benjaminmark@bsky.social", "text": "Develop southern know from wall financial even decade particularly yeah. #ai", "date": "2024-06-28", "hashtags": ["#ai"]}, {"id": 4, "user": "karen75@bsky.social", "text": "Some center few nation amount want. #election", "date": "2024-06-23", "hashtags": ["#election"]}, {"id": 5, "user": "breyes@bsky.social", "text": "Reduce Congress appear type fight where lead.", "date": "2024-06-17", "hashtags": []}, {"id": 6, "user": "dwilson@bsky.social", "text": "Wrong baby final chance decision in share knowledge example. #ai", "date": "2024-06-13", "hashtags": ["#ai"]}, {"id": 7, "user": "samuel20@bsky.social", "text": "One car step arm almost report difficult learn. #music", "date": "2024-06-09", "hashtags": ["#music"]}, {"id": 8, "user": "amills@bsky.social", "text": "Blood employee trouble Mrs not paper heavy improve. #ai", "date": "2024-06-22", "hashtags": ["#ai"]}, {"id": 9, "user": "npatrick@bsky.social", "text": "Yourself thousand clear deep despite half think animal. #music", "date": "2024-06-28", "hashtags": ["#music"]}, {"id": 10, "user": "bellis@bsky.social", "text": "Item though material again civil. #ai", "date": "2024-06-24", "hashtags": ["#ai"]}, {"id": 11, "user": "deborahford@bsky.social", "text": "Pass walk behind position north. #music #news", "date": "2024-06-03", "hashtags": ["#music", "#news"]}, {"id": 12, "user": "nancybender@bsky.social", "text": "Item maintain accept away image.", "date": "2024-06-21", "hashtags": []}, {"id": 13, "user": "reedmichael@bsky.social", "text": "Song close another industry population rate without price. #fun", "date": "2024-06-07", "hashtags": ["#fun"]}, {"id": 14, "user": "kylemartin@bsky.social", "text": "Night weight north opportunity understand whose sport huge because have.", "date": "2024-06-24", "hashtags": []}, {"id": 15, "user": "gregory82@bsky.social", "text": "Party piece in outside here by this American.", "date": "2024-06-06", "hashtags": []}, {"id": 16, "user": "chadbean@bsky.social", "text": "Since among already marriage early reach. #music", "date": "2024-06-22", "hashtags": ["#music"]}, {"id": 17, "user": "john84@bsky.social", "text": "Yard local American white claim little specific street security with.", "date": "2024-06-02", "hashtags": []}, {"id": 18, "user": "ymayer@bsky.social", "text": "Someone yet leader certain picture style. #music", "date": "2024-06-17", "hashtags": ["#music"]}, {"id": 19, "user": "ryan55@bsky.social", "text": "Head seat man similar road no executive throughout worry miss.", "date": "2024-06-18", "hashtags": []}, {"id": 20, "user": "daniellogan@bsky.social", "text": "Year before grow police draw. #election", "date": "2024-06-09", "hashtags": ["#election"]}, {"id": 21, "user": "alexander47@bsky.social", "text": "Western challenge range wear health discussion meeting church must. #election #climate", "date": "2024-06-26", "hashtags": ["#election", "#climate"]}, {"id": 22, "user": "kristine10@bsky.social", "text": "Happy side describe easy ten. #sports #fun", "date": "2024-06-20", "hashtags": ["#sports", "#fun"]}, {"id": 23, "user": "bhenderson@bsky.social", "text": "Save direction appear total pay meeting him some know energy. #election", "date": "2024-06-06", "hashtags": ["#election"]}, {"id": 24, "user": "omarsmith@bsky.social", "text": "Lawyer thing Congress beautiful city sport trial strong.", "date": "2024-06-02", "hashtags": []}, {"id": 25, "user": "jeremygreen@bsky.social", "text": "Draw also another break lose hair little star traditional leg its. #sports", "date": "2024-06-23", "hashtags": ["#sports"]}, {"id": 26, "user": "aaronmartinez@bsky.social", "text": "Mention gun speak training. #python #bsky", "date": "2024-06-28", "hashtags": ["#python", "#bsky"]}, {"id": 27, "user": "christine62@bsky.social", "text": "That person high remain follow college.", "date": "2024-06-29", "hashtags": []}, {"id": 28, "user": "nicole43@bsky.social", "text": "Force benefit role this traditional travel seem film.", "date": "2024-06-07", "hashtags": []}, {"id": 29, "user": "joshua59@bsky.social", "text": "Effect able able voice seat education however parent whom not. #election", "date": "2024-06-22", "hashtags": ["#election"]}, {"id": 30, "user": "fryedavid@bsky.social", "text": "Animal point rather stop tax more back why. #sports #music", "date": "2024-06-18", "hashtags": ["#sports", "#music"]}, {"id": 31, "user": "sandra63@bsky.social", "text": "Development commercial boy art center minute. #news", "date": "2024-06-24", "hashtags": ["#news"]}, {"id": 32, "user": "esparzagilbert@bsky.social", "text": "Little until long property job I. #news #election", "date": "2024-06-25", "hashtags": ["#news", "#election"]}, {"id": 33, "user": "johnfinley@bsky.social", "text": "Include material remain serve policy especially same outside.", "date": "2024-06-27", "hashtags": []}, {"id": 34, "user": "lesliegarcia@bsky.social", "text": "Pick wear year world write so everything. #bsky", "date": "2024-06-07", "hashtags": ["#bsky"]}, {"id": 35, "user": "daniel50@bsky.social", "text": "Fall building high pressure deep. #python", "date": "2024-06-28", "hashtags": ["#python"]}, {"id": 36, "user": "tyler94@bsky.social", "text": "Kind policy leg time little rather risk strategy example.", "date": "2024-06-03", "hashtags": []}, {"id": 37, "user": "david61@bsky.social", "text": "Statement stage budget hotel pass suffer every plan happy present. #music #election", "date": "2024-06-06", "hashtags": ["#music", "#election"]}, {"id": 38, "user": "cranesandra@bsky.social", "text": "Friend management while result animal old. #ai", "date": "2024-06-11", "hashtags": ["#ai"]}, {"id": 39, "user": "meganthomas@bsky.social", "text": "Owner ten treat it such. #news", "date": "2024-06-29", "hashtags": ["#news"]}, {"id": 40, "user": "rodrigueznicole@bsky.social", "text": "Hour born total production control how approach many scene.", "date": "2024-06-19", "hashtags": []}, {"id": 41, "user": "gibsonphillip@bsky.social", "text": "Another act state nearly cover.", "date": "2024-06-05", "hashtags": []}, {"id": 42, "user": "madisondavis@bsky.social", "text": "Exactly know explain task different decade risk into. #election", "date": "2024-06-12", "hashtags": ["#election"]}, {"id": 43, "user": "cameron04@bsky.social", "text": "Successful first learn on call moment focus each occur. #election", "date": "2024-06-07", "hashtags": ["#election"]}, {"id": 44, "user": "kimberly17@bsky.social", "text": "Agreement easy drop fund article ago head above member major. #bsky", "date": "2024-06-24", "hashtags": ["#bsky"]}, {"id": 45, "user": "amiranda@bsky.social", "text": "Law health budget could would. #news", "date": "2024-06-14", "hashtags": ["#news"]}, {"id": 46, "user": "ritadaugherty@bsky.social", "text": "Writer grow sound difference agency west case develop.", "date": "2024-06-21", "hashtags": []}, {"id": 47, "user": "barrystephen@bsky.social", "text": "Oil who report least cultural weight score business. #election #bsky", "date": "2024-06-02", "hashtags": ["#election", "#bsky"]}, {"id": 48, "user": "yshaffer@bsky.social", "text": "Top news approach skin something listen. #streamlit", "date": "2024-06-25", "hashtags": ["#streamlit"]}, {"id": 49, "user": "wilsonlaura@bsky.social", "text": "Carry compare style use. #bsky", "date": "2024-06-25", "hashtags": ["#bsky"]}, {"id": 50, "user": "wrightjoseph@bsky.social", "text": "Sing behind civil debate effect investment practice.", "date": "2024-06-22", "hashtags": []}, {"id": 51, "user": "jjohnson@bsky.social", "text": "Spring list development order night. #sports", "date": "2024-06-10", "hashtags": ["#sports"]}, {"id": 52, "user": "liuchristopher@bsky.social", "text": "Option draw rest this get better president wonder.", "date": "2024-06-23", "hashtags": []}, {"id": 53, "user": "patricianelson@bsky.social", "text": "Culture quite late key enjoy like near little adult.", "date": "2024-06-05", "hashtags": []}, {"id": 54, "user": "jordan06@bsky.social", "text": "Show its lawyer natural stage. #python", "date": "2024-06-08", "hashtags": ["#python"]}, {"id": 55, "user": "nwalker@bsky.social", "text": "Want cost ahead buy college even purpose article need. #streamlit", "date": "2024-06-05", "hashtags": ["#streamlit"]}, {"id": 56, "user": "carmenvalenzuela@bsky.social", "text": "Paper top attack growth hand manager down send. #streamlit", "date": "2024-06-27", "hashtags": ["#streamlit"]}, {"id": 57, "user": "carrrandall@bsky.social", "text": "Bit continue worry section factor much.", "date": "2024-06-02", "hashtags": []}, {"id": 58, "user": "donna98@bsky.social", "text": "Affect style which simple must. #sports #climate", "date": "2024-06-17", "hashtags": ["#sports", "#climate"]}, {"id": 59, "user": "umccann@bsky.social", "text": "Ready western generation improve live director me.", "date": "2024-06-21", "hashtags": []}, {"id": 60, "user": "thomasthomas@bsky.social", "text": "Consumer Mr attorney common nice last only. #music #python", "date": "2024-06-27", "hashtags": ["#music", "#python"]}, {"id": 61, "user": "drakelaura@bsky.social", "text": "Sure old citizen hear order. #fun #sports", "date": "2024-06-13", "hashtags": ["#fun", "#sports"]}, {"id": 62, "user": "hsimpson@bsky.social", "text": "Action reason often through few condition.", "date": "2024-06-13", "hashtags": []}, {"id": 63, "user": "glennwatts@bsky.social", "text": "Be fall evening ten laugh sometimes computer teach report. #ai", "date": "2024-06-25", "hashtags": ["#ai"]}, {"id": 64, "user": "guzmanclaudia@bsky.social", "text": "Very professor among present view city.", "date": "2024-06-01", "hashtags": []}, {"id": 65, "user": "traceymaldonado@bsky.social", "text": "President close growth important sell base. #python", "date": "2024-06-15", "hashtags": ["#python"]}, {"id": 66, "user": "randallroberts@bsky.social", "text": "Speak hot turn this strong him whether idea huge side. #news #ai", "date": "2024-06-14", "hashtags": ["#news", "#ai"]}, {"id": 67, "user": "lrogers@bsky.social", "text": "Floor head reach south political item sometimes quality role. #ai", "date": "2024-06-01", "hashtags": ["#ai"]}, {"id": 68, "user": "hodgesjohn@bsky.social", "text": "Me seek commercial answer.", "date": "2024-06-22", "hashtags": []}, {"id": 69, "user": "latoyaibarra@bsky.social", "text": "Economic myself dinner economic hair conference southern rate add energy. #sports", "date": "2024-06-14", "hashtags": ["#sports"]}, {"id": 70, "user": "fordkevin@bsky.social", "text": "Eat there whether trade according term raise improve worker. #python", "date": "2024-06-21", "hashtags": ["#python"]}, {"id": 71, "user": "kevin28@bsky.social", "text": "Scene according record effect.", "date": "2024-06-26", "hashtags": []}, {"id": 72, "user": "sarahmcintosh@bsky.social", "text": "Despite issue week believe administration as like investment mouth. #news #streamlit", "date": "2024-06-23", "hashtags": ["#news", "#streamlit"]}, {"id": 73, "user": "zcarlson@bsky.social", "text": "Force news artist purpose hand before never around decade. #python", "date": "2024-06-28", "hashtags": ["#python"]}, {"id": 74, "user": "dmartin@bsky.social", "text": "City growth should administration.", "date": "2024-06-13", "hashtags": []}, {"id": 75, "user": "amurray@bsky.social", "text": "Race score everyone serve road physical.", "date": "2024-06-23", "hashtags": []}, {"id": 76, "user": "carpenterheather@bsky.social", "text": "During trip campaign position parent seek present everybody person behind according.", "date": "2024-06-04", "hashtags": []}, {"id": 77, "user": "timothyhernandez@bsky.social", "text": "Pick every receive very card.", "date": "2024-06-24", "hashtags": []}, {"id": 78, "user": "mary46@bsky.social", "text": "Either word life my treatment current them. #music", "date": "2024-06-28", "hashtags": ["#music"]}, {"id": 79, "user": "athompson@bsky.social", "text": "Whom player cost hot six throughout pressure create. #news", "date": "2024-06-18", "hashtags": ["#news"]}, {"id": 80, "user": "billyedwards@bsky.social", "text": "Store film chance create son wall company relationship find without. #ai", "date": "2024-06-15", "hashtags": ["#ai"]}, {"id": 81, "user": "kerry08@bsky.social", "text": "Company school try here first travel without. #fun", "date": "2024-06-21", "hashtags": ["#fun"]}, {"id": 82, "user": "erika21@bsky.social", "text": "Side model approach least suggest.", "date": "2024-06-20", "hashtags": []}, {"id": 83, "user": "arthurpatton@bsky.social", "text": "Enter answer identify sea despite stand past treat.", "date": "2024-06-02", "hashtags": []}, {"id": 84, "user": "rduncan@bsky.social", "text": "Figure between price cultural successful entire father head political couple. #bsky #sports", "date": "2024-06-01", "hashtags": ["#bsky", "#sports"]}, {"id": 85, "user": "plawrence@bsky.social", "text": "Fly skin strategy positive wind.", "date": "2024-06-23", "hashtags": []}, {"id": 86, "user": "jgallagher@bsky.social", "text": "Season lot make follow describe happy generation lead. #election", "date": "2024-06-21", "hashtags": ["#election"]}, {"id": 87, "user": "rcox@bsky.social", "text": "Team else half develop bag country affect or program none. #ai", "date": "2024-06-01", "hashtags": ["#ai"]}, {"id": 88, "user": "codytrevino@bsky.social", "text": "However both every culture ok out. #ai", "date": "2024-06-13", "hashtags": ["#ai"]}, {"id": 89, "user": "jenniferparks@bsky.social", "text": "Than religious husband wrong article behavior.", "date": "2024-06-06", "hashtags": []}, {"id": 90, "user": "turnerlisa@bsky.social", "text": "Why who hold economic car pressure.", "date": "2024-06-18", "hashtags": []}, {"id": 91, "user": "markgoodman@bsky.social", "text": "Economic us pay case majority hope history film growth language bank. #climate", "date": "2024-06-12", "hashtags": ["#climate"]}, {"id": 92, "user": "iparsons@bsky.social", "text": "Couple day likely herself value half.", "date": "2024-06-05", "hashtags": []}, {"id": 93, "user": "ariasjennifer@bsky.social", "text": "Different purpose two feel these. #bsky #news", "date": "2024-06-17", "hashtags": ["#bsky", "#news"]}, {"id": 94, "user": "jade71@bsky.social", "text": "Trial road effort catch popular. #python", "date": "2024-06-10", "hashtags": ["#python"]}, {"id": 95, "user": "deborahpeters@bsky.social", "text": "Catch try I standard position accept. #election", "date": "2024-06-23", "hashtags": ["#election"]}, {"id": 96, "user": "cindy77@bsky.social", "text": "Figure attack commercial heavy shoulder network office threat crime adult. #news #bsky", "date": "2024-06-25", "hashtags": ["#news", "#bsky"]}, {"id": 97, "user": "forbesdana@bsky.social", "text": "Sure soldier someone task partner inside debate. #python #climate", "date": "2024-06-01", "hashtags": ["#python", "#climate"]}, {"id": 98, "user": "tjohnson@bsky.social", "text": "Member within her market man same finish writer. #fun", "date": "2024-06-08", "hashtags": ["#fun"]}, {"id": 99, "user": "xrogers@bsky.social", "text": "Special add federal throughout those. #fun", "date": "2024-06-08", "hashtags": ["#fun"]}, {"id": 100, "user": "brian92@bsky.social", "text": "So fight full age five item senior between. #climate", "date": "2024-06-11", "hashtags": ["#climate"]}]