[{"batch_size": 1, "current_classifier_results": {"accuracy": 0.0, "runtime_seconds": 5.518526395161946}, "prompt_batched_classifier_results": {"accuracy": 1.0, "runtime_seconds": 4.678289890289307}}, {"batch_size": 2, "current_classifier_results": {"accuracy": 0.6666666666666666, "runtime_seconds": 5.701984961827596}, "prompt_batched_classifier_results": {"accuracy": 1.0, "runtime_seconds": 3.3980265458424888}}, {"batch_size": 3, "current_classifier_results": {"accuracy": 0.4444444444444444, "runtime_seconds": 9.359577576319376}, "prompt_batched_classifier_results": {"accuracy": 1.0, "runtime_seconds": 4.631826877593994}}, {"batch_size": 5, "current_classifier_results": {"accuracy": 0.6, "runtime_seconds": 7.894061088562012}, "prompt_batched_classifier_results": {"accuracy": 1.0, "runtime_seconds": 6.859663248062134}}, {"batch_size": 8, "current_classifier_results": {"accuracy": 0.5, "runtime_seconds": 10.906725565592447}, "prompt_batched_classifier_results": {"accuracy": 0.9583333333333334, "runtime_seconds": 6.176764329274495}}, {"batch_size": 10, "current_classifier_results": {"accuracy": 0.4666666666666667, "runtime_seconds": 9.28485099474589}, "prompt_batched_classifier_results": {"accuracy": 0.9666666666666667, "runtime_seconds": 8.336514314015707}}, {"batch_size": 12, "current_classifier_results": {"accuracy": 0.5, "runtime_seconds": 9.806070725123087}, "prompt_batched_classifier_results": {"accuracy": 0.9166666666666666, "runtime_seconds": 7.79278826713562}}, {"batch_size": 15, "current_classifier_results": {"accuracy": 0.4222222222222222, "runtime_seconds": 10.472617149353027}, "prompt_batched_classifier_results": {"accuracy": 0.9333333333333333, "runtime_seconds": 9.299468914667765}}, {"batch_size": 20, "current_classifier_results": {"accuracy": 0.48333333333333334, "runtime_seconds": 12.32787036895752}, "prompt_batched_classifier_results": {"accuracy": 0.9833333333333333, "runtime_seconds": 12.519447724024454}}, {"batch_size": 25, "current_classifier_results": {"accuracy": 0.52, "runtime_seconds": 12.080442428588867}, "prompt_batched_classifier_results": {"accuracy": 0.64, "runtime_seconds": 16.421465635299683}}, {"batch_size": 30, "current_classifier_results": {"accuracy": 0.5, "runtime_seconds": 16.21881898244222}, "prompt_batched_classifier_results": {"accuracy": 0.3111111111111111, "runtime_seconds": 16.34294605255127}}]